setup.py
TracIMAPAuth.egg-info/PKG-INFO
TracIMAPAuth.egg-info/SOURCES.txt
TracIMAPAuth.egg-info/dependency_links.txt
TracIMAPAuth.egg-info/entry_points.txt
TracIMAPAuth.egg-info/requires.txt
TracIMAPAuth.egg-info/top_level.txt
imapauth/__init__.py
imapauth/store.py
