Metadata-Version: 1.0
Name: TracIMAPAuth
Version: 1.0
Summary: An AccountManager password store that uses imaplib to check against an IMAP server.
Home-page: http://trac-hacks.org/wiki/IMAPAuthPlugin
Author: Noah Kantrowitz
Author-email: coderanger@yahoo.com
License: BSD
Keywords: trac plugin accountmanager
Platform: UNKNOWN
Classifier: Framework :: Trac
